{
  "factors": {
    "vr_10": {
      "ic": -0.033066,
      "ic_abs": 0.033066,
      "spread": -0.1069,
      "samples": 31798,
      "updated": "2026-04-29",
      "source": "B_system_random"
    },
    "pct_1d": {
      "ic": -0.033519,
      "ic_abs": 0.033519,
      "spread": -0.1087,
      "samples": 31798,
      "updated": "2026-04-29",
      "source": "B_system_random"
    },
    "price_ma10": {
      "ic": -0.049498,
      "ic_abs": 0.049498,
      "spread": -0.1817,
      "samples": 31798,
      "updated": "2026-04-29",
      "source": "B_system_random"
    },
    "price_ma5": {
      "ic": -0.044973,
      "ic_abs": 0.044973,
      "spread": -0.1212,
      "samples": 31798,
      "updated": "2026-04-29",
      "source": "B_system_random"
    },
    "pct_5d": {
      "ic": -0.04841,
      "ic_abs": 0.04841,
      "spread": -0.1691,
      "samples": 31798,
      "updated": "2026-04-29",
      "source": "B_system_random"
    },
    "pct_10d": {
      "ic": -0.034455,
      "ic_abs": 0.034455,
      "spread": -0.1196,
      "samples": 31798,
      "updated": "2026-04-29",
      "source": "B_system_random"
    },
    "price_ma20": {
      "ic": -0.033567,
      "ic_abs": 0.033567,
      "spread": -0.1222,
      "samples": 31798,
      "updated": "2026-04-29",
      "source": "B_system_random"
    },
    "vr_20": {
      "ic": -0.022427,
      "ic_abs": 0.022427,
      "spread": -0.0601,
      "samples": 31798,
      "updated": "2026-04-29",
      "source": "B_system_random"
    },
    "cci_20": {
      "ic": -0.016133,
      "ic_abs": 0.016133,
      "spread": -0.1252,
      "samples": 31798,
      "updated": "2026-04-29",
      "source": "B_system_random"
    },
    "boll_30": {
      "ic": -0.016386,
      "ic_abs": 0.016386,
      "spread": -0.1295,
      "samples": 31798,
      "updated": "2026-04-29",
      "source": "B_system_random"
    },
    "boll_20": {
      "ic": -0.016481,
      "ic_abs": 0.016481,
      "spread": -0.1652,
      "samples": 31798,
      "updated": "2026-04-29",
      "source": "B_system_random"
    },
    "rsi_9": {
      "ic": -0.020366,
      "ic_abs": 0.020366,
      "spread": -0.1722,
      "samples": 31798,
      "updated": "2026-04-29",
      "source": "B_system_random"
    },
    "rsi_6": {
      "ic": -0.017331,
      "ic_abs": 0.017331,
      "spread": -0.1134,
      "samples": 31798,
      "updated": "2026-04-29",
      "source": "B_system_random"
    },
    "cci_14": {
      "ic": -0.012983,
      "ic_abs": 0.012983,
      "spread": -0.0535,
      "samples": 31798,
      "updated": "2026-04-29",
      "source": "B_system_random"
    },
    "kdj_k": {
      "ic": -0.01918,
      "ic_abs": 0.01918,
      "spread": -0.1795,
      "samples": 31798,
      "updated": "2026-04-29",
      "source": "B_system_random"
    },
    "kdj_d": {
      "ic": -0.016466,
      "ic_abs": 0.016466,
      "spread": -0.1365,
      "samples": 31798,
      "updated": "2026-04-29",
      "source": "B_system_random"
    },
    "price_ma30": {
      "ic": -0.022781,
      "ic_abs": 0.022781,
      "spread": -0.0488,
      "samples": 31798,
      "updated": "2026-04-29",
      "source": "B_system_random"
    },
    "rsi_14": {
      "ic": -0.019781,
      "ic_abs": 0.019781,
      "spread": -0.188,
      "samples": 31798,
      "updated": "2026-04-29",
      "source": "B_system_random"
    },
    "kdj_j": {
      "ic": -0.018449,
      "ic_abs": 0.018449,
      "spread": -0.1736,
      "samples": 31798,
      "updated": "2026-04-29",
      "source": "B_system_random"
    },
    "amplitude": {
      "ic": 0.024707,
      "ic_abs": 0.024707,
      "spread": 0.1946,
      "samples": 31798,
      "updated": "2026-04-29",
      "source": "B_system_random"
    },
    "vr_5": {
      "ic": -0.001257,
      "ic_abs": 0.001257,
      "spread": -0.0773,
      "samples": 31798,
      "updated": "2026-04-29",
      "source": "B_system_random"
    },
    "rsi_26": {
      "ic": -0.008136,
      "ic_abs": 0.008136,
      "spread": -0.0688,
      "samples": 31798,
      "updated": "2026-04-29",
      "source": "B_system_random"
    },
    "pct_20d": {
      "ic": -0.013776,
      "ic_abs": 0.013776,
      "spread": -0.1062,
      "samples": 31798,
      "updated": "2026-04-29",
      "source": "B_system_random"
    },
    "pct_60d": {
      "ic": -0.014959,
      "ic_abs": 0.014959,
      "spread": -0.1448,
      "samples": 31798,
      "updated": "2026-04-29",
      "source": "B_system_random"
    },
    "pct_30d": {
      "ic": -0.005572,
      "ic_abs": 0.005572,
      "spread": -0.0438,
      "samples": 31798,
      "updated": "2026-04-29",
      "source": "B_system_random"
    },
    "price_ma60": {
      "ic": -0.017772,
      "ic_abs": 0.017772,
      "spread": -0.1567,
      "samples": 31798,
      "updated": "2026-04-29",
      "source": "B_system_random"
    }
  },
  "rules": {},
  "metadata": {
    "version": "v4.7",
    "created": "2026-04-29",
    "total_samples": 0,
    "last_updated": "2026-04-29 22:25"
  }
}