{
  "factors": {
    "vr_10": {
      "ic": -0.041845,
      "ic_abs": 0.041845,
      "spread": -0.0864,
      "samples": 51789,
      "updated": "2026-04-30",
      "source": "B_system_random"
    },
    "pct_1d": {
      "ic": -0.03338,
      "ic_abs": 0.03338,
      "spread": -0.1634,
      "samples": 51789,
      "updated": "2026-04-30",
      "source": "B_system_random"
    },
    "price_ma10": {
      "ic": -0.060296,
      "ic_abs": 0.060296,
      "spread": -0.2025,
      "samples": 51789,
      "updated": "2026-04-30",
      "source": "B_system_random"
    },
    "price_ma5": {
      "ic": -0.054113,
      "ic_abs": 0.054113,
      "spread": -0.1486,
      "samples": 51789,
      "updated": "2026-04-30",
      "source": "B_system_random"
    },
    "pct_5d": {
      "ic": -0.060707,
      "ic_abs": 0.060707,
      "spread": -0.183,
      "samples": 51789,
      "updated": "2026-04-30",
      "source": "B_system_random"
    },
    "pct_10d": {
      "ic": -0.038051,
      "ic_abs": 0.038051,
      "spread": -0.1401,
      "samples": 51789,
      "updated": "2026-04-30",
      "source": "B_system_random"
    },
    "price_ma20": {
      "ic": -0.039228,
      "ic_abs": 0.039228,
      "spread": -0.0929,
      "samples": 51789,
      "updated": "2026-04-30",
      "source": "B_system_random"
    },
    "vr_20": {
      "ic": -0.012286,
      "ic_abs": 0.012286,
      "spread": -0.0007,
      "samples": 51789,
      "updated": "2026-04-30",
      "source": "B_system_random"
    },
    "cci_20": {
      "ic": -0.02252,
      "ic_abs": 0.02252,
      "spread": -0.1429,
      "samples": 51789,
      "updated": "2026-04-30",
      "source": "B_system_random"
    },
    "boll_30": {
      "ic": -0.01927,
      "ic_abs": 0.01927,
      "spread": -0.1243,
      "samples": 51789,
      "updated": "2026-04-30",
      "source": "B_system_random"
    },
    "boll_20": {
      "ic": -0.021138,
      "ic_abs": 0.021138,
      "spread": -0.1466,
      "samples": 51789,
      "updated": "2026-04-30",
      "source": "B_system_random"
    },
    "rsi_9": {
      "ic": -0.023238,
      "ic_abs": 0.023238,
      "spread": -0.1907,
      "samples": 51789,
      "updated": "2026-04-30",
      "source": "B_system_random"
    },
    "rsi_6": {
      "ic": -0.024728,
      "ic_abs": 0.024728,
      "spread": -0.1881,
      "samples": 51789,
      "updated": "2026-04-30",
      "source": "B_system_random"
    },
    "cci_14": {
      "ic": -0.020142,
      "ic_abs": 0.020142,
      "spread": -0.1514,
      "samples": 51789,
      "updated": "2026-04-30",
      "source": "B_system_random"
    },
    "kdj_k": {
      "ic": -0.025644,
      "ic_abs": 0.025644,
      "spread": -0.2443,
      "samples": 51789,
      "updated": "2026-04-30",
      "source": "B_system_random"
    },
    "kdj_d": {
      "ic": -0.020838,
      "ic_abs": 0.020838,
      "spread": -0.1836,
      "samples": 51789,
      "updated": "2026-04-30",
      "source": "B_system_random"
    },
    "price_ma30": {
      "ic": -0.027904,
      "ic_abs": 0.027904,
      "spread": -0.0349,
      "samples": 51789,
      "updated": "2026-04-30",
      "source": "B_system_random"
    },
    "rsi_14": {
      "ic": -0.017758,
      "ic_abs": 0.017758,
      "spread": -0.1167,
      "samples": 51789,
      "updated": "2026-04-30",
      "source": "B_system_random"
    },
    "kdj_j": {
      "ic": -0.025939,
      "ic_abs": 0.025939,
      "spread": -0.2506,
      "samples": 51789,
      "updated": "2026-04-30",
      "source": "B_system_random"
    },
    "amplitude": {
      "ic": 0.013276,
      "ic_abs": 0.013276,
      "spread": 0.1627,
      "samples": 51789,
      "updated": "2026-04-30",
      "source": "B_system_random"
    },
    "vr_5": {
      "ic": 0.004469,
      "ic_abs": 0.004469,
      "spread": 0.0211,
      "samples": 51789,
      "updated": "2026-04-30",
      "source": "B_system_random"
    },
    "rsi_26": {
      "ic": -0.008645,
      "ic_abs": 0.008645,
      "spread": -0.0503,
      "samples": 51789,
      "updated": "2026-04-30",
      "source": "B_system_random"
    },
    "pct_20d": {
      "ic": -0.016498,
      "ic_abs": 0.016498,
      "spread": -0.0706,
      "samples": 51789,
      "updated": "2026-04-30",
      "source": "B_system_random"
    },
    "pct_60d": {
      "ic": -0.014825,
      "ic_abs": 0.014825,
      "spread": -0.1418,
      "samples": 51789,
      "updated": "2026-04-30",
      "source": "B_system_random"
    },
    "pct_30d": {
      "ic": -0.008574,
      "ic_abs": 0.008574,
      "spread": -0.0655,
      "samples": 51789,
      "updated": "2026-04-30",
      "source": "B_system_random"
    },
    "price_ma60": {
      "ic": -0.021799,
      "ic_abs": 0.021799,
      "spread": -0.1253,
      "samples": 51789,
      "updated": "2026-04-30",
      "source": "B_system_random"
    },
    "williams": {
      "ic": -0.018472,
      "ic_abs": 0.018472,
      "spread": -0.1381,
      "samples": 51789,
      "updated": "2026-04-30",
      "source": "B_system_random"
    },
    "vol_ratio": {
      "ic": 0.004353,
      "ic_abs": 0.004353,
      "spread": 0.0029,
      "samples": 51789,
      "updated": "2026-04-30",
      "source": "B_system_random"
    }
  },
  "rules": {
    "RSI55-65|KDJ_J<0": {
      "type": "RSI+KDJ",
      "condition": "RSI55-65|KDJ_J<0",
      "factor1": "rsi_14",
      "range1": "55-65",
      "factor2": "kdj_j",
      "range2": "<0",
      "up_ratio": 56.28,
      "avg_ret": 0.466,
      "samples": 93324,
      "ic": 0
    },
    "Pct-10%~-6%": {
      "type": "Pct",
      "condition": "Pct-10%~-6%",
      "factor": "pct_1d",
      "range": "-10%~-6%",
      "up_ratio": 55.39,
      "avg_ret": 0.6288,
      "samples": 155376,
      "ic": -0.027823
    },
    "RSI<25|KDJ_J0-20": {
      "type": "RSI+KDJ",
      "condition": "RSI<25|KDJ_J0-20",
      "factor1": "rsi_14",
      "range1": "<25",
      "factor2": "kdj_j",
      "range2": "0-20",
      "up_ratio": 55.23,
      "avg_ret": 0.2595,
      "samples": 246228,
      "ic": 0
    },
    "RSI<25|Pct-6%~-2%": {
      "type": "RSI+Pct",
      "condition": "RSI<25|Pct-6%~-2%",
      "factor1": "rsi_14",
      "range1": "<25",
      "factor2": "pct_1d",
      "range2": "-6%~-2%",
      "up_ratio": 55.13,
      "avg_ret": 0.1474,
      "samples": 105408,
      "ic": 0
    },
    "RSI<25|WILL<-80": {
      "type": "RSI+WILL",
      "condition": "RSI<25|WILL<-80",
      "factor1": "rsi_14",
      "range1": "<25",
      "factor2": "williams",
      "range2": "<-80",
      "up_ratio": 54.24,
      "avg_ret": 0.2198,
      "samples": 503962,
      "ic": 0
    },
    "RSI<25": {
      "type": "RSI",
      "condition": "RSI<25",
      "factor": "rsi_14",
      "range": "<25",
      "up_ratio": 54.13,
      "avg_ret": 0.2361,
      "samples": 814933,
      "ic": -0.004706
    },
    "RSI45-55|KDJ_J<0": {
      "type": "RSI+KDJ",
      "condition": "RSI45-55|KDJ_J<0",
      "factor1": "rsi_14",
      "range1": "45-55",
      "factor2": "kdj_j",
      "range2": "<0",
      "up_ratio": 53.47,
      "avg_ret": 0.2065,
      "samples": 206148,
      "ic": 0
    },
    "RSI35-45|KDJ_J<0": {
      "type": "RSI+KDJ",
      "condition": "RSI35-45|KDJ_J<0",
      "factor1": "rsi_14",
      "range1": "35-45",
      "factor2": "kdj_j",
      "range2": "<0",
      "up_ratio": 53.42,
      "avg_ret": 0.1619,
      "samples": 227052,
      "ic": 0
    },
    "RSI55-65|Pct-6%~-2%": {
      "type": "RSI+Pct",
      "condition": "RSI55-65|Pct-6%~-2%",
      "factor1": "rsi_14",
      "range1": "55-65",
      "factor2": "pct_1d",
      "range2": "-6%~-2%",
      "up_ratio": 53.76,
      "avg_ret": 0.3642,
      "samples": 268188,
      "ic": 0
    },
    "KDJ_J<0": {
      "type": "KDJ_J",
      "condition": "KDJ_J<0",
      "factor": "kdj_j",
      "range": "<0",
      "up_ratio": 54.12,
      "avg_ret": 0.2197,
      "samples": 1417992,
      "ic": -0.0086
    },
    "RSI35-45|BOLL<0.15": {
      "type": "RSI+BOLL",
      "condition": "RSI35-45|BOLL<0.15",
      "factor1": "rsi_14",
      "range1": "35-45",
      "factor2": "boll_20",
      "range2": "<0.15",
      "up_ratio": 53.9,
      "avg_ret": 0.1829,
      "samples": 289584,
      "ic": 0
    },
    "RSI25-35|KDJ_J<0": {
      "type": "RSI+KDJ",
      "condition": "RSI25-35|KDJ_J<0",
      "factor1": "rsi_14",
      "range1": "25-35",
      "factor2": "kdj_j",
      "range2": "<0",
      "up_ratio": 54.35,
      "avg_ret": 0.1853,
      "samples": 154284,
      "ic": 0
    },
    "RSI<25|BOLL0.15-0.3": {
      "type": "RSI+BOLL",
      "condition": "RSI<25|BOLL0.15-0.3",
      "factor1": "rsi_14",
      "range1": "<25",
      "factor2": "boll_20",
      "range2": "0.15-0.3",
      "up_ratio": 51.07,
      "avg_ret": 0.0737,
      "samples": 178500,
      "ic": 0
    },
    "BOLL<0.15": {
      "type": "BOLL",
      "condition": "BOLL<0.15",
      "factor": "boll_20",
      "range": "<0.15",
      "up_ratio": 54.22,
      "avg_ret": 0.1987,
      "samples": 1505551,
      "ic": -0.007482
    },
    "RSI25-35|BOLL<0.15": {
      "type": "RSI+BOLL",
      "condition": "RSI25-35|BOLL<0.15",
      "factor1": "rsi_14",
      "range1": "25-35",
      "factor2": "boll_20",
      "range2": "<0.15",
      "up_ratio": 54.28,
      "avg_ret": 0.2195,
      "samples": 287160,
      "ic": 0
    },
    "RSI<25|BOLL<0.15": {
      "type": "RSI+BOLL",
      "condition": "RSI<25|BOLL<0.15",
      "factor1": "rsi_14",
      "range1": "<25",
      "factor2": "boll_20",
      "range2": "<0.15",
      "up_ratio": 55.36,
      "avg_ret": 0.1913,
      "samples": 191376,
      "ic": 0
    },
    "RSI55-65|WILL-80~-60": {
      "type": "RSI+WILL",
      "condition": "RSI55-65|WILL-80~-60",
      "factor1": "rsi_14",
      "range1": "55-65",
      "factor2": "williams",
      "range2": "-80~-60",
      "up_ratio": 54.03,
      "avg_ret": 0.3192,
      "samples": 274908,
      "ic": 0
    },
    "RSI<25|KDJ_J20-50": {
      "type": "RSI+KDJ",
      "condition": "RSI<25|KDJ_J20-50",
      "factor1": "rsi_14",
      "range1": "<25",
      "factor2": "kdj_j",
      "range2": "20-50",
      "up_ratio": 53.44,
      "avg_ret": 0.2414,
      "samples": 128376,
      "ic": 0
    },
    "RSI35-45|WILL<-80": {
      "type": "RSI+WILL",
      "condition": "RSI35-45|WILL<-80",
      "factor1": "rsi_14",
      "range1": "35-45",
      "factor2": "williams",
      "range2": "<-80",
      "up_ratio": 52.66,
      "avg_ret": 0.173,
      "samples": 1049600,
      "ic": 0
    },
    "RSI65-75|KDJ_J0-20": {
      "type": "RSI+KDJ",
      "condition": "RSI65-75|KDJ_J0-20",
      "factor1": "rsi_14",
      "range1": "65-75",
      "factor2": "kdj_j",
      "range2": "0-20",
      "up_ratio": 53.07,
      "avg_ret": 0.3718,
      "samples": 42348,
      "ic": 0
    },
    "RSI<25|Pct-2%~+2%": {
      "type": "RSI+Pct",
      "condition": "RSI<25|Pct-2%~+2%",
      "factor1": "rsi_14",
      "range1": "<25",
      "factor2": "pct_1d",
      "range2": "-2%~+2%",
      "up_ratio": 53.23,
      "avg_ret": 0.1518,
      "samples": 327312,
      "ic": 0
    },
    "RSI35-45|Pct-6%~-2%": {
      "type": "RSI+Pct",
      "condition": "RSI35-45|Pct-6%~-2%",
      "factor1": "rsi_14",
      "range1": "35-45",
      "factor2": "pct_1d",
      "range2": "-6%~-2%",
      "up_ratio": 52.74,
      "avg_ret": 0.1553,
      "samples": 278088,
      "ic": 0
    },
    "WILL<-80": {
      "type": "WILL",
      "condition": "WILL<-80",
      "factor": "williams",
      "range": "<-80",
      "up_ratio": 53.12,
      "avg_ret": 0.1835,
      "samples": 3566760,
      "ic": -0.003571
    },
    "RSI<25|KDJ_J<0": {
      "type": "RSI+KDJ",
      "condition": "RSI<25|KDJ_J<0",
      "factor1": "rsi_14",
      "range1": "<25",
      "factor2": "kdj_j",
      "range2": "<0",
      "up_ratio": 54.28,
      "avg_ret": 0.1812,
      "samples": 78852,
      "ic": 0
    },
    "RSI45-55|BOLL0.7-0.85": {
      "type": "RSI+BOLL",
      "condition": "RSI45-55|BOLL0.7-0.85",
      "factor1": "rsi_14",
      "range1": "45-55",
      "factor2": "boll_20",
      "range2": "0.7-0.85",
      "up_ratio": 49.12,
      "avg_ret": 0.2468,
      "samples": 220764,
      "ic": 0
    },
    "Pct-6%~-2%": {
      "type": "Pct",
      "condition": "Pct-6%~-2%",
      "factor": "pct_1d",
      "range": "-6%~-2%",
      "up_ratio": 52.77,
      "avg_ret": 0.2286,
      "samples": 2400113,
      "ic": -0.027823
    },
    "RSI55-65|WILL-60~-40": {
      "type": "RSI+WILL",
      "condition": "RSI55-65|WILL-60~-40",
      "factor1": "rsi_14",
      "range1": "55-65",
      "factor2": "williams",
      "range2": "-60~-40",
      "up_ratio": 51.15,
      "avg_ret": 0.2568,
      "samples": 1188161,
      "ic": 0
    },
    "RSI55-65|BOLL0.5-0.7": {
      "type": "RSI+BOLL",
      "condition": "RSI55-65|BOLL0.5-0.7",
      "factor1": "rsi_14",
      "range1": "55-65",
      "factor2": "boll_20",
      "range2": "0.5-0.7",
      "up_ratio": 52.23,
      "avg_ret": 0.2853,
      "samples": 1379319,
      "ic": 0
    },
    "RSI45-55|Pct-6%~-2%": {
      "type": "RSI+Pct",
      "condition": "RSI45-55|Pct-6%~-2%",
      "factor1": "rsi_14",
      "range1": "45-55",
      "factor2": "pct_1d",
      "range2": "-6%~-2%",
      "up_ratio": 52.16,
      "avg_ret": 0.2048,
      "samples": 307260,
      "ic": 0
    },
    "RSI55-65|KDJ_J0-20": {
      "type": "RSI+KDJ",
      "condition": "RSI55-65|KDJ_J0-20",
      "factor1": "rsi_14",
      "range1": "55-65",
      "factor2": "kdj_j",
      "range2": "0-20",
      "up_ratio": 52.6,
      "avg_ret": 0.2635,
      "samples": 233208,
      "ic": 0
    },
    "RSI45-55|KDJ_J50-80": {
      "type": "RSI+KDJ",
      "condition": "RSI45-55|KDJ_J50-80",
      "factor1": "rsi_14",
      "range1": "45-55",
      "factor2": "kdj_j",
      "range2": "50-80",
      "up_ratio": 50.62,
      "avg_ret": 0.2201,
      "samples": 802636,
      "ic": 0
    },
    "KDJ_J0-20": {
      "type": "KDJ_J",
      "condition": "KDJ_J0-20",
      "factor": "kdj_j",
      "range": "0-20",
      "up_ratio": 52.6,
      "avg_ret": 0.2177,
      "samples": 3045767,
      "ic": -0.0086
    },
    "RSI25-35|KDJ_J0-20": {
      "type": "RSI+KDJ",
      "condition": "RSI25-35|KDJ_J0-20",
      "factor1": "rsi_14",
      "range1": "25-35",
      "factor2": "kdj_j",
      "range2": "0-20",
      "up_ratio": 52.81,
      "avg_ret": 0.1743,
      "samples": 343428,
      "ic": 0
    },
    "RSI45-55|WILL-80~-60": {
      "type": "RSI+WILL",
      "condition": "RSI45-55|WILL-80~-60",
      "factor1": "rsi_14",
      "range1": "45-55",
      "factor2": "williams",
      "range2": "-80~-60",
      "up_ratio": 51.26,
      "avg_ret": 0.2298,
      "samples": 956150,
      "ic": 0
    },
    "RSI45-55|WILL-40~-20": {
      "type": "RSI+WILL",
      "condition": "RSI45-55|WILL-40~-20",
      "factor1": "rsi_14",
      "range1": "45-55",
      "factor2": "williams",
      "range2": "-40~-20",
      "up_ratio": 49.1,
      "avg_ret": 0.1751,
      "samples": 517933,
      "ic": 0
    },
    "RSI55-65|BOLL0.3-0.5": {
      "type": "RSI+BOLL",
      "condition": "RSI55-65|BOLL0.3-0.5",
      "factor1": "rsi_14",
      "range1": "55-65",
      "factor2": "boll_20",
      "range2": "0.3-0.5",
      "up_ratio": 50.95,
      "avg_ret": 0.1695,
      "samples": 151140,
      "ic": 0
    },
    "RSI25-35|WILL<-80": {
      "type": "RSI+WILL",
      "condition": "RSI25-35|WILL<-80",
      "factor1": "rsi_14",
      "range1": "25-35",
      "factor2": "williams",
      "range2": "<-80",
      "up_ratio": 52.9,
      "avg_ret": 0.1592,
      "samples": 1016063,
      "ic": 0
    },
    "RSI45-55|BOLL0.5-0.7": {
      "type": "RSI+BOLL",
      "condition": "RSI45-55|BOLL0.5-0.7",
      "factor1": "rsi_14",
      "range1": "45-55",
      "factor2": "boll_20",
      "range2": "0.5-0.7",
      "up_ratio": 49.74,
      "avg_ret": 0.1693,
      "samples": 1224995,
      "ic": 0
    },
    "RSI45-55|KDJ_J0-20": {
      "type": "RSI+KDJ",
      "condition": "RSI45-55|KDJ_J0-20",
      "factor1": "rsi_14",
      "range1": "45-55",
      "factor2": "kdj_j",
      "range2": "0-20",
      "up_ratio": 51.31,
      "avg_ret": 0.1962,
      "samples": 412128,
      "ic": 0
    },
    "BOLL0.5-0.7": {
      "type": "BOLL",
      "condition": "BOLL0.5-0.7",
      "factor": "boll_20",
      "range": "0.5-0.7",
      "up_ratio": 50.69,
      "avg_ret": 0.2198,
      "samples": 3136472,
      "ic": -0.007482
    },
    "RSI45-55|WILL<-80": {
      "type": "RSI+WILL",
      "condition": "RSI45-55|WILL<-80",
      "factor1": "rsi_14",
      "range1": "45-55",
      "factor2": "williams",
      "range2": "<-80",
      "up_ratio": 52.77,
      "avg_ret": 0.1977,
      "samples": 329400,
      "ic": 0
    },
    "RSI45-55": {
      "type": "RSI",
      "condition": "RSI45-55",
      "factor": "rsi_14",
      "range": "45-55",
      "up_ratio": 50.44,
      "avg_ret": 0.1945,
      "samples": 3645880,
      "ic": -0.004706
    },
    "RSI45-55|KDJ_J>80": {
      "type": "RSI+KDJ",
      "condition": "RSI45-55|KDJ_J>80",
      "factor1": "rsi_14",
      "range1": "45-55",
      "factor2": "kdj_j",
      "range2": ">80",
      "up_ratio": 48.71,
      "avg_ret": 0.1638,
      "samples": 291840,
      "ic": 0
    },
    "RSI55-65|KDJ_J20-50": {
      "type": "RSI+KDJ",
      "condition": "RSI55-65|KDJ_J20-50",
      "factor1": "rsi_14",
      "range1": "55-65",
      "factor2": "kdj_j",
      "range2": "20-50",
      "up_ratio": 50.96,
      "avg_ret": 0.2437,
      "samples": 788843,
      "ic": 0
    },
    "RSI25-35|Pct-2%~+2%": {
      "type": "RSI+Pct",
      "condition": "RSI25-35|Pct-2%~+2%",
      "factor1": "rsi_14",
      "range1": "25-35",
      "factor2": "pct_1d",
      "range2": "-2%~+2%",
      "up_ratio": 51.19,
      "avg_ret": 0.1526,
      "samples": 1342872,
      "ic": 0
    },
    "RSI45-55|Pct-2%~+2%": {
      "type": "RSI+Pct",
      "condition": "RSI45-55|Pct-2%~+2%",
      "factor1": "rsi_14",
      "range1": "45-55",
      "factor2": "pct_1d",
      "range2": "-2%~+2%",
      "up_ratio": 50.03,
      "avg_ret": 0.1553,
      "samples": 2453459,
      "ic": 0
    },
    "RSI25-35": {
      "type": "RSI",
      "condition": "RSI25-35",
      "factor": "rsi_14",
      "range": "25-35",
      "up_ratio": 51.62,
      "avg_ret": 0.1633,
      "samples": 1897244,
      "ic": -0.004706
    },
    "RSI45-55|BOLL0.3-0.5": {
      "type": "RSI+BOLL",
      "condition": "RSI45-55|BOLL0.3-0.5",
      "factor1": "rsi_14",
      "range1": "45-55",
      "factor2": "boll_20",
      "range2": "0.3-0.5",
      "up_ratio": 51.02,
      "avg_ret": 0.2056,
      "samples": 1351623,
      "ic": 0
    },
    "RSI45-55|BOLL0.15-0.3": {
      "type": "RSI+BOLL",
      "condition": "RSI45-55|BOLL0.15-0.3",
      "factor1": "rsi_14",
      "range1": "45-55",
      "factor2": "boll_20",
      "range2": "0.15-0.3",
      "up_ratio": 51.65,
      "avg_ret": 0.1833,
      "samples": 243132,
      "ic": 0
    },
    "RSI45-55|BOLL<0.15": {
      "type": "RSI+BOLL",
      "condition": "RSI45-55|BOLL<0.15",
      "factor1": "rsi_14",
      "range1": "45-55",
      "factor2": "boll_20",
      "range2": "<0.15",
      "up_ratio": 52.01,
      "avg_ret": 0.1383,
      "samples": 50568,
      "ic": 0
    },
    "RSI35-45|KDJ_J0-20": {
      "type": "RSI+KDJ",
      "condition": "RSI35-45|KDJ_J0-20",
      "factor1": "rsi_14",
      "range1": "35-45",
      "factor2": "kdj_j",
      "range2": "0-20",
      "up_ratio": 51.81,
      "avg_ret": 0.172,
      "samples": 511902,
      "ic": 0
    },
    "RSI45-55|WILL-60~-40": {
      "type": "RSI+WILL",
      "condition": "RSI45-55|WILL-60~-40",
      "factor1": "rsi_14",
      "range1": "45-55",
      "factor2": "williams",
      "range2": "-60~-40",
      "up_ratio": 50.45,
      "avg_ret": 0.1903,
      "samples": 892255,
      "ic": 0
    },
    "WILL-80~-60": {
      "type": "WILL",
      "condition": "WILL-80~-60",
      "factor": "williams",
      "range": "-80~-60",
      "up_ratio": 51.27,
      "avg_ret": 0.2244,
      "samples": 3367718,
      "ic": -0.003571
    },
    "BOLL0.15-0.3": {
      "type": "BOLL",
      "condition": "BOLL0.15-0.3",
      "factor": "boll_20",
      "range": "0.15-0.3",
      "up_ratio": 50.94,
      "avg_ret": 0.1523,
      "samples": 2506855,
      "ic": -0.007482
    },
    "WILL-60~-40": {
      "type": "WILL",
      "condition": "WILL-60~-40",
      "factor": "williams",
      "range": "-60~-40",
      "up_ratio": 49.61,
      "avg_ret": 0.1874,
      "samples": 3374627,
      "ic": -0.003571
    },
    "RSI35-45|Pct-2%~+2%": {
      "type": "RSI+Pct",
      "condition": "RSI35-45|Pct-2%~+2%",
      "factor1": "rsi_14",
      "range1": "35-45",
      "factor2": "pct_1d",
      "range2": "-2%~+2%",
      "up_ratio": 49.81,
      "avg_ret": 0.1308,
      "samples": 2136014,
      "ic": 0
    },
    "RSI35-45|KDJ_J20-50": {
      "type": "RSI+KDJ",
      "condition": "RSI35-45|KDJ_J20-50",
      "factor1": "rsi_14",
      "range1": "35-45",
      "factor2": "kdj_j",
      "range2": "20-50",
      "up_ratio": 49.86,
      "avg_ret": 0.1695,
      "samples": 727536,
      "ic": 0
    },
    "RSI65-75|Pct-6%~-2%": {
      "type": "RSI+Pct",
      "condition": "RSI65-75|Pct-6%~-2%",
      "factor1": "rsi_14",
      "range1": "65-75",
      "factor2": "pct_1d",
      "range2": "-6%~-2%",
      "up_ratio": 51.28,
      "avg_ret": 0.4134,
      "samples": 123708,
      "ic": 0
    },
    "RSI35-45|BOLL0.15-0.3": {
      "type": "RSI+BOLL",
      "condition": "RSI35-45|BOLL0.15-0.3",
      "factor1": "rsi_14",
      "range1": "35-45",
      "factor2": "boll_20",
      "range2": "0.15-0.3",
      "up_ratio": 50.77,
      "avg_ret": 0.182,
      "samples": 904626,
      "ic": 0
    },
    "KDJ_J20-50": {
      "type": "KDJ_J",
      "condition": "KDJ_J20-50",
      "factor": "kdj_j",
      "range": "20-50",
      "up_ratio": 50.49,
      "avg_ret": 0.1993,
      "samples": 3931819,
      "ic": -0.0086
    },
    "RSI25-35|Pct-6%~-2%": {
      "type": "RSI+Pct",
      "condition": "RSI25-35|Pct-6%~-2%",
      "factor1": "rsi_14",
      "range1": "25-35",
      "factor2": "pct_1d",
      "range2": "-6%~-2%",
      "up_ratio": 53.32,
      "avg_ret": 0.0835,
      "samples": 185976,
      "ic": 0
    },
    "RSI25-35|KDJ_J20-50": {
      "type": "RSI+KDJ",
      "condition": "RSI25-35|KDJ_J20-50",
      "factor1": "rsi_14",
      "range1": "25-35",
      "factor2": "kdj_j",
      "range2": "20-50",
      "up_ratio": 51.2,
      "avg_ret": 0.1636,
      "samples": 321744,
      "ic": 0
    },
    "RSI55-65": {
      "type": "RSI",
      "condition": "RSI55-65",
      "factor": "rsi_14",
      "range": "55-65",
      "up_ratio": 50.33,
      "avg_ret": 0.2585,
      "samples": 3598243,
      "ic": -0.004706
    },
    "RSI45-55|BOLL>0.85": {
      "type": "RSI+BOLL",
      "condition": "RSI45-55|BOLL>0.85",
      "factor1": "rsi_14",
      "range1": "45-55",
      "factor2": "boll_20",
      "range2": ">0.85",
      "up_ratio": 50.33,
      "avg_ret": 0.3217,
      "samples": 53544,
      "ic": 0
    },
    "RSI25-35|WILL-80~-60": {
      "type": "RSI+WILL",
      "condition": "RSI25-35|WILL-80~-60",
      "factor1": "rsi_14",
      "range1": "25-35",
      "factor2": "williams",
      "range2": "-80~-60",
      "up_ratio": 49.88,
      "avg_ret": 0.1638,
      "samples": 400084,
      "ic": 0
    },
    "Pct-2%~+2%": {
      "type": "Pct",
      "condition": "Pct-2%~+2%",
      "factor": "pct_1d",
      "range": "-2%~+2%",
      "up_ratio": 49.8,
      "avg_ret": 0.1533,
      "samples": 10644141,
      "ic": -0.027823
    },
    "RSI<25|WILL-80~-60": {
      "type": "RSI+WILL",
      "condition": "RSI<25|WILL-80~-60",
      "factor1": "rsi_14",
      "range1": "<25",
      "factor2": "williams",
      "range2": "-80~-60",
      "up_ratio": 53.39,
      "avg_ret": 0.303,
      "samples": 71292,
      "ic": 0
    },
    "RSI55-65|KDJ_J50-80": {
      "type": "RSI+KDJ",
      "condition": "RSI55-65|KDJ_J50-80",
      "factor1": "rsi_14",
      "range1": "55-65",
      "factor2": "kdj_j",
      "range2": "50-80",
      "up_ratio": 49.85,
      "avg_ret": 0.2331,
      "samples": 1072806,
      "ic": 0
    },
    "RSI35-45": {
      "type": "RSI",
      "condition": "RSI35-45",
      "factor": "rsi_14",
      "range": "35-45",
      "up_ratio": 50.01,
      "avg_ret": 0.1408,
      "samples": 3080555,
      "ic": -0.004706
    },
    "RSI55-65|Pct+2%~+6%": {
      "type": "RSI+Pct",
      "condition": "RSI55-65|Pct+2%~+6%",
      "factor1": "rsi_14",
      "range1": "55-65",
      "factor2": "pct_1d",
      "range2": "+2%~+6%",
      "up_ratio": 50.02,
      "avg_ret": 0.3941,
      "samples": 321288,
      "ic": 0
    },
    "RSI45-55|Pct+2%~+6%": {
      "type": "RSI+Pct",
      "condition": "RSI45-55|Pct+2%~+6%",
      "factor1": "rsi_14",
      "range1": "45-55",
      "factor2": "pct_1d",
      "range2": "+2%~+6%",
      "up_ratio": 50.07,
      "avg_ret": 0.2934,
      "samples": 266664,
      "ic": 0
    },
    "RSI45-55|KDJ_J20-50": {
      "type": "RSI+KDJ",
      "condition": "RSI45-55|KDJ_J20-50",
      "factor1": "rsi_14",
      "range1": "45-55",
      "factor2": "kdj_j",
      "range2": "20-50",
      "up_ratio": 50.15,
      "avg_ret": 0.1728,
      "samples": 869531,
      "ic": 0
    },
    "RSI>75|Pct-2%~+2%": {
      "type": "RSI+Pct",
      "condition": "RSI>75|Pct-2%~+2%",
      "factor1": "rsi_14",
      "range1": ">75",
      "factor2": "pct_1d",
      "range2": "-2%~+2%",
      "up_ratio": 47.03,
      "avg_ret": 0.1281,
      "samples": 270804,
      "ic": 0
    },
    "RSI65-75|BOLL0.5-0.7": {
      "type": "RSI+BOLL",
      "condition": "RSI65-75|BOLL0.5-0.7",
      "factor1": "rsi_14",
      "range1": "65-75",
      "factor2": "boll_20",
      "range2": "0.5-0.7",
      "up_ratio": 50.56,
      "avg_ret": 0.2118,
      "samples": 138912,
      "ic": 0
    },
    "RSI>75|BOLL0.7-0.85": {
      "type": "RSI+BOLL",
      "condition": "RSI>75|BOLL0.7-0.85",
      "factor1": "rsi_14",
      "range1": ">75",
      "factor2": "boll_20",
      "range2": "0.7-0.85",
      "up_ratio": 48.53,
      "avg_ret": 0.2199,
      "samples": 83184,
      "ic": 0
    },
    "KDJ_J50-80": {
      "type": "KDJ_J",
      "condition": "KDJ_J50-80",
      "factor": "kdj_j",
      "range": "50-80",
      "up_ratio": 48.95,
      "avg_ret": 0.1847,
      "samples": 4144741,
      "ic": -0.0086
    },
    "RSI65-75|KDJ_J20-50": {
      "type": "RSI+KDJ",
      "condition": "RSI65-75|KDJ_J20-50",
      "factor1": "rsi_14",
      "range1": "65-75",
      "factor2": "kdj_j",
      "range2": "20-50",
      "up_ratio": 48.76,
      "avg_ret": 0.2262,
      "samples": 204672,
      "ic": 0
    },
    "BOLL0.3-0.5": {
      "type": "BOLL",
      "condition": "BOLL0.3-0.5",
      "factor": "boll_20",
      "range": "0.3-0.5",
      "up_ratio": 49.22,
      "avg_ret": 0.1424,
      "samples": 3139011,
      "ic": -0.007482
    },
    "RSI55-65|Pct-2%~+2%": {
      "type": "RSI+Pct",
      "condition": "RSI55-65|Pct-2%~+2%",
      "factor1": "rsi_14",
      "range1": "55-65",
      "factor2": "pct_1d",
      "range2": "-2%~+2%",
      "up_ratio": 49.78,
      "avg_ret": 0.1834,
      "samples": 2310894,
      "ic": 0
    },
    "RSI25-35|Pct+2%~+6%": {
      "type": "RSI+Pct",
      "condition": "RSI25-35|Pct+2%~+6%",
      "factor1": "rsi_14",
      "range1": "25-35",
      "factor2": "pct_1d",
      "range2": "+2%~+6%",
      "up_ratio": 49.75,
      "avg_ret": 0.2692,
      "samples": 86700,
      "ic": 0
    },
    "RSI45-55|WILL>-20": {
      "type": "RSI+WILL",
      "condition": "RSI45-55|WILL>-20",
      "factor1": "rsi_14",
      "range1": "45-55",
      "factor2": "williams",
      "range2": ">-20",
      "up_ratio": 46.36,
      "avg_ret": 0.1254,
      "samples": 157632,
      "ic": 0
    },
    "RSI25-35|BOLL0.15-0.3": {
      "type": "RSI+BOLL",
      "condition": "RSI25-35|BOLL0.15-0.3",
      "factor1": "rsi_14",
      "range1": "25-35",
      "factor2": "boll_20",
      "range2": "0.15-0.3",
      "up_ratio": 50.57,
      "avg_ret": 0.128,
      "samples": 538954,
      "ic": 0
    },
    "BOLL0.7-0.85": {
      "type": "BOLL",
      "condition": "BOLL0.7-0.85",
      "factor": "boll_20",
      "range": "0.7-0.85",
      "up_ratio": 48.89,
      "avg_ret": 0.2122,
      "samples": 2423726,
      "ic": -0.007482
    },
    "RSI55-65|Pct+6%~+10%": {
      "type": "RSI+Pct",
      "condition": "RSI55-65|Pct+6%~+10%",
      "factor1": "rsi_14",
      "range1": "55-65",
      "factor2": "pct_1d",
      "range2": "+6%~+10%",
      "up_ratio": 47.57,
      "avg_ret": 0.3112,
      "samples": 43536,
      "ic": 0
    },
    "RSI25-35|WILL-60~-40": {
      "type": "RSI+WILL",
      "condition": "RSI25-35|WILL-60~-40",
      "factor1": "rsi_14",
      "range1": "25-35",
      "factor2": "williams",
      "range2": "-60~-40",
      "up_ratio": 49.24,
      "avg_ret": 0.1759,
      "samples": 75372,
      "ic": 0
    },
    "RSI25-35|KDJ_J50-80": {
      "type": "RSI+KDJ",
      "condition": "RSI25-35|KDJ_J50-80",
      "factor1": "rsi_14",
      "range1": "25-35",
      "factor2": "kdj_j",
      "range2": "50-80",
      "up_ratio": 48.85,
      "avg_ret": 0.1205,
      "samples": 159264,
      "ic": 0
    },
    "RSI>75|KDJ_J50-80": {
      "type": "RSI+KDJ",
      "condition": "RSI>75|KDJ_J50-80",
      "factor1": "rsi_14",
      "range1": ">75",
      "factor2": "kdj_j",
      "range2": "50-80",
      "up_ratio": 46.46,
      "avg_ret": 0.1541,
      "samples": 149184,
      "ic": 0
    },
    "WILL-40~-20": {
      "type": "WILL",
      "condition": "WILL-40~-20",
      "factor": "williams",
      "range": "-40~-20",
      "up_ratio": 48.6,
      "avg_ret": 0.2,
      "samples": 3341010,
      "ic": -0.003571
    },
    "RSI65-75|WILL-60~-40": {
      "type": "RSI+WILL",
      "condition": "RSI65-75|WILL-60~-40",
      "factor1": "rsi_14",
      "range1": "65-75",
      "factor2": "williams",
      "range2": "-60~-40",
      "up_ratio": 48.2,
      "avg_ret": 0.1487,
      "samples": 185208,
      "ic": 0
    },
    "RSI55-65|KDJ_J>80": {
      "type": "RSI+KDJ",
      "condition": "RSI55-65|KDJ_J>80",
      "factor1": "rsi_14",
      "range1": "55-65",
      "factor2": "kdj_j",
      "range2": ">80",
      "up_ratio": 48.52,
      "avg_ret": 0.2161,
      "samples": 478090,
      "ic": 0
    },
    "RSI>75|BOLL>0.85": {
      "type": "RSI+BOLL",
      "condition": "RSI>75|BOLL>0.85",
      "factor1": "rsi_14",
      "range1": ">75",
      "factor2": "boll_20",
      "range2": ">0.85",
      "up_ratio": 46.08,
      "avg_ret": 0.1372,
      "samples": 193380,
      "ic": 0
    },
    "RSI55-65|BOLL0.7-0.85": {
      "type": "RSI+BOLL",
      "condition": "RSI55-65|BOLL0.7-0.85",
      "factor1": "rsi_14",
      "range1": "55-65",
      "factor2": "boll_20",
      "range2": "0.7-0.85",
      "up_ratio": 49.61,
      "avg_ret": 0.2204,
      "samples": 1019682,
      "ic": 0
    },
    "RSI55-65|WILL-40~-20": {
      "type": "RSI+WILL",
      "condition": "RSI55-65|WILL-40~-20",
      "factor1": "rsi_14",
      "range1": "55-65",
      "factor2": "williams",
      "range2": "-40~-20",
      "up_ratio": 49.88,
      "avg_ret": 0.2504,
      "samples": 1093151,
      "ic": 0
    },
    "RSI35-45|WILL-80~-60": {
      "type": "RSI+WILL",
      "condition": "RSI35-45|WILL-80~-60",
      "factor1": "rsi_14",
      "range1": "35-45",
      "factor2": "williams",
      "range2": "-80~-60",
      "up_ratio": 50.49,
      "avg_ret": 0.184,
      "samples": 964850,
      "ic": 0
    },
    "RSI65-75|Pct+6%~+10%": {
      "type": "RSI+Pct",
      "condition": "RSI65-75|Pct+6%~+10%",
      "factor1": "rsi_14",
      "range1": "65-75",
      "factor2": "pct_1d",
      "range2": "+6%~+10%",
      "up_ratio": 46.57,
      "avg_ret": 0.3481,
      "samples": 56076,
      "ic": 0
    },
    "RSI35-45|WILL-60~-40": {
      "type": "RSI+WILL",
      "condition": "RSI35-45|WILL-60~-40",
      "factor1": "rsi_14",
      "range1": "35-45",
      "factor2": "williams",
      "range2": "-60~-40",
      "up_ratio": 46.64,
      "avg_ret": 0.0766,
      "samples": 484728,
      "ic": 0
    },
    "RSI65-75|BOLL0.7-0.85": {
      "type": "RSI+BOLL",
      "condition": "RSI65-75|BOLL0.7-0.85",
      "factor1": "rsi_14",
      "range1": "65-75",
      "factor2": "boll_20",
      "range2": "0.7-0.85",
      "up_ratio": 48.27,
      "avg_ret": 0.2062,
      "samples": 521651,
      "ic": 0
    },
    "KDJ_J>80": {
      "type": "KDJ_J",
      "condition": "KDJ_J>80",
      "factor": "kdj_j",
      "range": ">80",
      "up_ratio": 47.12,
      "avg_ret": 0.1401,
      "samples": 2868567,
      "ic": -0.0086
    },
    "RSI35-45|KDJ_J50-80": {
      "type": "RSI+KDJ",
      "condition": "RSI35-45|KDJ_J50-80",
      "factor1": "rsi_14",
      "range1": "35-45",
      "factor2": "kdj_j",
      "range2": "50-80",
      "up_ratio": 48.14,
      "avg_ret": 0.0949,
      "samples": 357384,
      "ic": 0
    },
    "RSI>75|KDJ_J>80": {
      "type": "RSI+KDJ",
      "condition": "RSI>75|KDJ_J>80",
      "factor1": "rsi_14",
      "range1": ">75",
      "factor2": "kdj_j",
      "range2": ">80",
      "up_ratio": 44.51,
      "avg_ret": -0.0336,
      "samples": 289824,
      "ic": 0
    },
    "RSI35-45|BOLL0.3-0.5": {
      "type": "RSI+BOLL",
      "condition": "RSI35-45|BOLL0.3-0.5",
      "factor1": "rsi_14",
      "range1": "35-45",
      "factor2": "boll_20",
      "range2": "0.3-0.5",
      "up_ratio": 47.44,
      "avg_ret": 0.082,
      "samples": 1065576,
      "ic": 0
    },
    "Pct+2%~+6%": {
      "type": "Pct",
      "condition": "Pct+2%~+6%",
      "factor": "pct_1d",
      "range": "+2%~+6%",
      "up_ratio": 48.28,
      "avg_ret": 0.269,
      "samples": 2382136,
      "ic": -0.027823
    },
    "RSI65-75|WILL-40~-20": {
      "type": "RSI+WILL",
      "condition": "RSI65-75|WILL-40~-20",
      "factor1": "rsi_14",
      "range1": "65-75",
      "factor2": "williams",
      "range2": "-40~-20",
      "up_ratio": 48.02,
      "avg_ret": 0.2325,
      "samples": 899834,
      "ic": 0
    },
    "RSI65-75": {
      "type": "RSI",
      "condition": "RSI65-75",
      "factor": "rsi_14",
      "range": "65-75",
      "up_ratio": 47.58,
      "avg_ret": 0.2103,
      "samples": 2223904,
      "ic": -0.004706
    },
    "RSI55-65|BOLL>0.85": {
      "type": "RSI+BOLL",
      "condition": "RSI55-65|BOLL>0.85",
      "factor1": "rsi_14",
      "range1": "55-65",
      "factor2": "boll_20",
      "range2": ">0.85",
      "up_ratio": 47.83,
      "avg_ret": 0.25,
      "samples": 321216,
      "ic": 0
    },
    "RSI65-75|WILL>-20": {
      "type": "RSI+WILL",
      "condition": "RSI65-75|WILL>-20",
      "factor1": "rsi_14",
      "range1": "65-75",
      "factor2": "williams",
      "range2": ">-20",
      "up_ratio": 47.29,
      "avg_ret": 0.241,
      "samples": 700976,
      "ic": 0
    },
    "RSI55-65|WILL>-20": {
      "type": "RSI+WILL",
      "condition": "RSI55-65|WILL>-20",
      "factor1": "rsi_14",
      "range1": "55-65",
      "factor2": "williams",
      "range2": ">-20",
      "up_ratio": 46.93,
      "avg_ret": 0.2169,
      "samples": 414740,
      "ic": 0
    },
    "RSI>75|WILL-40~-20": {
      "type": "RSI+WILL",
      "condition": "RSI>75|WILL-40~-20",
      "factor1": "rsi_14",
      "range1": ">75",
      "factor2": "williams",
      "range2": "-40~-20",
      "up_ratio": 45.27,
      "avg_ret": -0.0015,
      "samples": 137472,
      "ic": 0
    },
    "RSI65-75|KDJ_J50-80": {
      "type": "RSI+KDJ",
      "condition": "RSI65-75|KDJ_J50-80",
      "factor1": "rsi_14",
      "range1": "65-75",
      "factor2": "kdj_j",
      "range2": "50-80",
      "up_ratio": 47.5,
      "avg_ret": 0.1826,
      "samples": 750194,
      "ic": 0
    },
    "BOLL>0.85": {
      "type": "BOLL",
      "condition": "BOLL>0.85",
      "factor": "boll_20",
      "range": ">0.85",
      "up_ratio": 46.73,
      "avg_ret": 0.1702,
      "samples": 1729709,
      "ic": -0.007482
    },
    "WILL>-20": {
      "type": "WILL",
      "condition": "WILL>-20",
      "factor": "williams",
      "range": ">-20",
      "up_ratio": 46.06,
      "avg_ret": 0.1021,
      "samples": 2493090,
      "ic": -0.003571
    },
    "RSI25-35|KDJ_J>80": {
      "type": "RSI+KDJ",
      "condition": "RSI25-35|KDJ_J>80",
      "factor1": "rsi_14",
      "range1": "25-35",
      "factor2": "kdj_j",
      "range2": ">80",
      "up_ratio": 47.73,
      "avg_ret": 0.1667,
      "samples": 44664,
      "ic": 0
    },
    "RSI25-35|BOLL0.3-0.5": {
      "type": "RSI+BOLL",
      "condition": "RSI25-35|BOLL0.3-0.5",
      "factor1": "rsi_14",
      "range1": "25-35",
      "factor2": "boll_20",
      "range2": "0.3-0.5",
      "up_ratio": 46.52,
      "avg_ret": 0.0727,
      "samples": 182352,
      "ic": 0
    },
    "RSI35-45|BOLL0.5-0.7": {
      "type": "RSI+BOLL",
      "condition": "RSI35-45|BOLL0.5-0.7",
      "factor1": "rsi_14",
      "range1": "35-45",
      "factor2": "boll_20",
      "range2": "0.5-0.7",
      "up_ratio": 47.35,
      "avg_ret": 0.1341,
      "samples": 134376,
      "ic": 0
    },
    "RSI65-75|Pct+2%~+6%": {
      "type": "RSI+Pct",
      "condition": "RSI65-75|Pct+2%~+6%",
      "factor1": "rsi_14",
      "range1": "65-75",
      "factor2": "pct_1d",
      "range2": "+2%~+6%",
      "up_ratio": 46.46,
      "avg_ret": 0.285,
      "samples": 252696,
      "ic": 0
    },
    "RSI65-75|Pct-2%~+2%": {
      "type": "RSI+Pct",
      "condition": "RSI65-75|Pct-2%~+2%",
      "factor1": "rsi_14",
      "range1": "65-75",
      "factor2": "pct_1d",
      "range2": "-2%~+2%",
      "up_ratio": 47.55,
      "avg_ret": 0.1454,
      "samples": 1305769,
      "ic": 0
    },
    "RSI35-45|WILL-40~-20": {
      "type": "RSI+WILL",
      "condition": "RSI35-45|WILL-40~-20",
      "factor1": "rsi_14",
      "range1": "35-45",
      "factor2": "williams",
      "range2": "-40~-20",
      "up_ratio": 45.39,
      "avg_ret": 0.0216,
      "samples": 114336,
      "ic": 0
    },
    "RSI35-45|KDJ_J>80": {
      "type": "RSI+KDJ",
      "condition": "RSI35-45|KDJ_J>80",
      "factor1": "rsi_14",
      "range1": "35-45",
      "factor2": "kdj_j",
      "range2": ">80",
      "up_ratio": 46.52,
      "avg_ret": 0.1095,
      "samples": 163944,
      "ic": 0
    },
    "RSI>75|WILL>-20": {
      "type": "RSI+WILL",
      "condition": "RSI>75|WILL>-20",
      "factor1": "rsi_14",
      "range1": ">75",
      "factor2": "williams",
      "range2": ">-20",
      "up_ratio": 43.66,
      "avg_ret": -0.1846,
      "samples": 407398,
      "ic": 0
    },
    "RSI>75": {
      "type": "RSI",
      "condition": "RSI>75",
      "factor": "rsi_14",
      "range": ">75",
      "up_ratio": 43.27,
      "avg_ret": -0.1832,
      "samples": 996234,
      "ic": -0.004706
    },
    "RSI65-75|BOLL>0.85": {
      "type": "RSI+BOLL",
      "condition": "RSI65-75|BOLL>0.85",
      "factor1": "rsi_14",
      "range1": "65-75",
      "factor2": "boll_20",
      "range2": ">0.85",
      "up_ratio": 45.74,
      "avg_ret": 0.108,
      "samples": 406714,
      "ic": 0
    },
    "Pct+6%~+10%": {
      "type": "Pct",
      "condition": "Pct+6%~+10%",
      "factor": "pct_1d",
      "range": "+6%~+10%",
      "up_ratio": 43.29,
      "avg_ret": -0.1155,
      "samples": 216948,
      "ic": -0.027823
    },
    "RSI65-75|KDJ_J>80": {
      "type": "RSI+KDJ",
      "condition": "RSI65-75|KDJ_J>80",
      "factor1": "rsi_14",
      "range1": "65-75",
      "factor2": "kdj_j",
      "range2": ">80",
      "up_ratio": 46.15,
      "avg_ret": 0.1546,
      "samples": 407028,
      "ic": 0
    },
    "RSI>75|Pct+2%~+6%": {
      "type": "RSI+Pct",
      "condition": "RSI>75|Pct+2%~+6%",
      "factor1": "rsi_14",
      "range1": ">75",
      "factor2": "pct_1d",
      "range2": "+2%~+6%",
      "up_ratio": 42.84,
      "avg_ret": -0.0832,
      "samples": 146652,
      "ic": 0
    },
    "Pct>+10%": {
      "type": "Pct",
      "condition": "Pct>+10%",
      "factor": "pct_1d",
      "range": ">+10%",
      "up_ratio": 38.3,
      "avg_ret": -0.6778,
      "samples": 115200,
      "ic": -0.027823
    },
    "RSI35-45|Pct+2%~+6%": {
      "type": "RSI+Pct",
      "condition": "RSI35-45|Pct+2%~+6%",
      "factor1": "rsi_14",
      "range1": "35-45",
      "factor2": "pct_1d",
      "range2": "+2%~+6%",
      "up_ratio": 46.99,
      "avg_ret": 0.1469,
      "samples": 189600,
      "ic": 0
    },
    "RSI>75|Pct>+10%": {
      "type": "RSI+Pct",
      "condition": "RSI>75|Pct>+10%",
      "factor1": "rsi_14",
      "range1": ">75",
      "factor2": "pct_1d",
      "range2": ">+10%",
      "up_ratio": 32.78,
      "avg_ret": -1.2943,
      "samples": 57804,
      "ic": 0
    },
    "RSI>75|Pct+6%~+10%": {
      "type": "RSI+Pct",
      "condition": "RSI>75|Pct+6%~+10%",
      "factor1": "rsi_14",
      "range1": ">75",
      "factor2": "pct_1d",
      "range2": "+6%~+10%",
      "up_ratio": 34.9,
      "avg_ret": -1.0672,
      "samples": 69852,
      "ic": 0
    },
    "RSI<25|Pct<-10%": {
      "type": "RSI+Pct",
      "condition": "RSI<25|Pct<-10%",
      "factor1": "rsi_14",
      "range1": "<25",
      "factor2": "pct_1d",
      "range2": "<-10%",
      "up_ratio": 71.21,
      "avg_ret": 1.084,
      "samples": 792,
      "ic": 0
    },
    "RSI55-65|Pct<-10%": {
      "type": "RSI+Pct",
      "condition": "RSI55-65|Pct<-10%",
      "factor1": "rsi_14",
      "range1": "55-65",
      "factor2": "pct_1d",
      "range2": "<-10%",
      "up_ratio": 61.54,
      "avg_ret": 0.9794,
      "samples": 624,
      "ic": 0
    },
    "RSI<25|Pct+2%~+6%": {
      "type": "RSI+Pct",
      "condition": "RSI<25|Pct+2%~+6%",
      "factor1": "rsi_14",
      "range1": "<25",
      "factor2": "pct_1d",
      "range2": "+2%~+6%",
      "up_ratio": 59.53,
      "avg_ret": 1.067,
      "samples": 2580,
      "ic": 0
    },
    "RSI<25|Pct-10%~-6%": {
      "type": "RSI+Pct",
      "condition": "RSI<25|Pct-10%~-6%",
      "factor1": "rsi_14",
      "range1": "<25",
      "factor2": "pct_1d",
      "range2": "-10%~-6%",
      "up_ratio": 58.33,
      "avg_ret": 0.7712,
      "samples": 1296,
      "ic": 0
    },
    "RSI>75|BOLL0.5-0.7": {
      "type": "RSI+BOLL",
      "condition": "RSI>75|BOLL0.5-0.7",
      "factor1": "rsi_14",
      "range1": ">75",
      "factor2": "boll_20",
      "range2": "0.5-0.7",
      "up_ratio": 58.0,
      "avg_ret": 0.3635,
      "samples": 600,
      "ic": 0
    },
    "Pct<-10%": {
      "type": "Pct",
      "condition": "Pct<-10%",
      "factor": "pct_1d",
      "range": "<-10%",
      "up_ratio": 57.89,
      "avg_ret": 0.7916,
      "samples": 3192,
      "ic": -0.036055
    },
    "RSI25-35|Pct-10%~-6%": {
      "type": "RSI+Pct",
      "condition": "RSI25-35|Pct-10%~-6%",
      "factor1": "rsi_14",
      "range1": "25-35",
      "factor2": "pct_1d",
      "range2": "-10%~-6%",
      "up_ratio": 57.6,
      "avg_ret": 0.7366,
      "samples": 1500,
      "ic": 0
    },
    "RSI35-45|Pct-10%~-6%": {
      "type": "RSI+Pct",
      "condition": "RSI35-45|Pct-10%~-6%",
      "factor1": "rsi_14",
      "range1": "35-45",
      "factor2": "pct_1d",
      "range2": "-10%~-6%",
      "up_ratio": 55.66,
      "avg_ret": 0.2909,
      "samples": 2544,
      "ic": 0
    },
    "RSI45-55|Pct-10%~-6%": {
      "type": "RSI+Pct",
      "condition": "RSI45-55|Pct-10%~-6%",
      "factor1": "rsi_14",
      "range1": "45-55",
      "factor2": "pct_1d",
      "range2": "-10%~-6%",
      "up_ratio": 55.51,
      "avg_ret": 0.5104,
      "samples": 2940,
      "ic": 0
    },
    "RSI65-75|KDJ_J<0": {
      "type": "RSI+KDJ",
      "condition": "RSI65-75|KDJ_J<0",
      "factor1": "rsi_14",
      "range1": "65-75",
      "factor2": "kdj_j",
      "range2": "<0",
      "up_ratio": 53.75,
      "avg_ret": 0.6399,
      "samples": 960,
      "ic": 0
    },
    "RSI55-65|Pct-10%~-6%": {
      "type": "RSI+Pct",
      "condition": "RSI55-65|Pct-10%~-6%",
      "factor1": "rsi_14",
      "range1": "55-65",
      "factor2": "pct_1d",
      "range2": "-10%~-6%",
      "up_ratio": 53.28,
      "avg_ret": 0.8895,
      "samples": 3288,
      "ic": 0
    },
    "RSI55-65|WILL<-80": {
      "type": "RSI+WILL",
      "condition": "RSI55-65|WILL<-80",
      "factor1": "rsi_14",
      "range1": "55-65",
      "factor2": "williams",
      "range2": "<-80",
      "up_ratio": 53.03,
      "avg_ret": 0.7095,
      "samples": 792,
      "ic": 0
    },
    "RSI35-45|WILL>-20": {
      "type": "RSI+WILL",
      "condition": "RSI35-45|WILL>-20",
      "factor1": "rsi_14",
      "range1": "35-45",
      "factor2": "williams",
      "range2": ">-20",
      "up_ratio": 50.91,
      "avg_ret": -0.1614,
      "samples": 660,
      "ic": 0
    },
    "RSI55-65|Pct>+10%": {
      "type": "RSI+Pct",
      "condition": "RSI55-65|Pct>+10%",
      "factor1": "rsi_14",
      "range1": "55-65",
      "factor2": "pct_1d",
      "range2": ">+10%",
      "up_ratio": 50.69,
      "avg_ret": 0.1493,
      "samples": 1728,
      "ic": 0
    },
    "RSI45-55|Pct+6%~+10%": {
      "type": "RSI+Pct",
      "condition": "RSI45-55|Pct+6%~+10%",
      "factor1": "rsi_14",
      "range1": "45-55",
      "factor2": "pct_1d",
      "range2": "+6%~+10%",
      "up_ratio": 50.4,
      "avg_ret": 0.3342,
      "samples": 3000,
      "ic": 0
    },
    "RSI>75|Pct-6%~-2%": {
      "type": "RSI+Pct",
      "condition": "RSI>75|Pct-6%~-2%",
      "factor1": "rsi_14",
      "range1": ">75",
      "factor2": "pct_1d",
      "range2": "-6%~-2%",
      "up_ratio": 50.0,
      "avg_ret": 0.3571,
      "samples": 3048,
      "ic": 0
    },
    "RSI>75|KDJ_J20-50": {
      "type": "RSI+KDJ",
      "condition": "RSI>75|KDJ_J20-50",
      "factor1": "rsi_14",
      "range1": ">75",
      "factor2": "kdj_j",
      "range2": "20-50",
      "up_ratio": 49.52,
      "avg_ret": 0.5909,
      "samples": 1260,
      "ic": 0
    },
    "RSI65-75|Pct-10%~-6%": {
      "type": "RSI+Pct",
      "condition": "RSI65-75|Pct-10%~-6%",
      "factor1": "rsi_14",
      "range1": "65-75",
      "factor2": "pct_1d",
      "range2": "-10%~-6%",
      "up_ratio": 49.18,
      "avg_ret": 0.4705,
      "samples": 2196,
      "ic": 0
    },
    "RSI<25|KDJ_J50-80": {
      "type": "RSI+KDJ",
      "condition": "RSI<25|KDJ_J50-80",
      "factor1": "rsi_14",
      "range1": "<25",
      "factor2": "kdj_j",
      "range2": "50-80",
      "up_ratio": 48.94,
      "avg_ret": 0.1563,
      "samples": 2256,
      "ic": 0
    },
    "RSI<25|BOLL0.3-0.5": {
      "type": "RSI+BOLL",
      "condition": "RSI<25|BOLL0.3-0.5",
      "factor1": "rsi_14",
      "range1": "<25",
      "factor2": "boll_20",
      "range2": "0.3-0.5",
      "up_ratio": 48.34,
      "avg_ret": 0.0431,
      "samples": 1812,
      "ic": 0
    },
    "RSI65-75|Pct<-10%": {
      "type": "RSI+Pct",
      "condition": "RSI65-75|Pct<-10%",
      "factor1": "rsi_14",
      "range1": "65-75",
      "factor2": "pct_1d",
      "range2": "<-10%",
      "up_ratio": 46.67,
      "avg_ret": 0.2013,
      "samples": 720,
      "ic": 0
    },
    "RSI65-75|Pct>+10%": {
      "type": "RSI+Pct",
      "condition": "RSI65-75|Pct>+10%",
      "factor1": "rsi_14",
      "range1": "65-75",
      "factor2": "pct_1d",
      "range2": ">+10%",
      "up_ratio": 45.79,
      "avg_ret": 0.0486,
      "samples": 2280,
      "ic": 0
    },
    "RSI65-75|BOLL0.3-0.5": {
      "type": "RSI+BOLL",
      "condition": "RSI65-75|BOLL0.3-0.5",
      "factor1": "rsi_14",
      "range1": "65-75",
      "factor2": "boll_20",
      "range2": "0.3-0.5",
      "up_ratio": 45.76,
      "avg_ret": 0.2803,
      "samples": 708,
      "ic": 0
    },
    "RSI35-45|Pct+6%~+10%": {
      "type": "RSI+Pct",
      "condition": "RSI35-45|Pct+6%~+10%",
      "factor1": "rsi_14",
      "range1": "35-45",
      "factor2": "pct_1d",
      "range2": "+6%~+10%",
      "up_ratio": 40.87,
      "avg_ret": -0.1733,
      "samples": 1380,
      "ic": 0
    },
    "RSI25-35|BOLL0.5-0.7": {
      "type": "RSI+BOLL",
      "condition": "RSI25-35|BOLL0.5-0.7",
      "factor1": "rsi_14",
      "range1": "25-35",
      "factor2": "boll_20",
      "range2": "0.5-0.7",
      "up_ratio": 40.68,
      "avg_ret": -0.2382,
      "samples": 708,
      "ic": 0
    },
    "RSI45-55|Pct>+10%": {
      "type": "RSI+Pct",
      "condition": "RSI45-55|Pct>+10%",
      "factor1": "rsi_14",
      "range1": "45-55",
      "factor2": "pct_1d",
      "range2": ">+10%",
      "up_ratio": 37.7,
      "avg_ret": -0.3646,
      "samples": 732,
      "ic": 0
    },
    "RSI35-45|BOLL0.7-0.85": {
      "type": "RSI+BOLL",
      "condition": "RSI35-45|BOLL0.7-0.85",
      "factor1": "rsi_14",
      "range1": "35-45",
      "factor2": "boll_20",
      "range2": "0.7-0.85",
      "up_ratio": 36.89,
      "avg_ret": -0.2686,
      "samples": 1236,
      "ic": 0
    },
    "RSI55-65|BOLL0.15-0.3": {
      "type": "RSI+BOLL",
      "condition": "RSI55-65|BOLL0.15-0.3",
      "factor1": "rsi_14",
      "range1": "55-65",
      "factor2": "boll_20",
      "range2": "0.15-0.3",
      "up_ratio": 33.33,
      "avg_ret": -0.1977,
      "samples": 612,
      "ic": 0
    },
    "PMA200.9-0.95": {
      "type": "PMA20",
      "condition": "PMA200.9-0.95",
      "factor": "price_ma20",
      "range": "0.9-0.95",
      "up_ratio": 54.59,
      "avg_ret": 0.2079,
      "samples": 5578,
      "ic": -0.039228
    },
    "CCI<-100": {
      "type": "CCI",
      "condition": "CCI<-100",
      "factor": "cci_14",
      "range": "<-100",
      "up_ratio": 53.59,
      "avg_ret": 0.2094,
      "samples": 7886,
      "ic": -0.020142
    },
    "Pct-2%~+2%|KDJ0-20": {
      "type": "Pct+KDJ",
      "condition": "Pct-2%~+2%|KDJ0-20",
      "factor1": "pct_1d",
      "range1": "-2%~+2%",
      "factor2": "kdj_j",
      "range2": "0-20",
      "up_ratio": 52.08,
      "avg_ret": 0.182,
      "samples": 6768,
      "ic": 0
    },
    "CCI-100~-50": {
      "type": "CCI",
      "condition": "CCI-100~-50",
      "factor": "cci_14",
      "range": "-100~-50",
      "up_ratio": 51.87,
      "avg_ret": 0.1745,
      "samples": 8374,
      "ic": -0.020142
    },
    "PMA50.95-1.0": {
      "type": "PMA5",
      "condition": "PMA50.95-1.0",
      "factor": "price_ma5",
      "range": "0.95-1.0",
      "up_ratio": 51.66,
      "avg_ret": 0.1693,
      "samples": 23496,
      "ic": -0.054113
    },
    "VR<80": {
      "type": "VR",
      "condition": "VR<80",
      "factor": "vr_20",
      "range": "<80",
      "up_ratio": 51.57,
      "avg_ret": 0.1478,
      "samples": 9407,
      "ic": -0.012286
    },
    "Pct-2%~+2%|VR<80": {
      "type": "Pct+VR",
      "condition": "Pct-2%~+2%|VR<80",
      "factor1": "pct_1d",
      "range1": "-2%~+2%",
      "factor2": "vr_20",
      "range2": "<80",
      "up_ratio": 51.25,
      "avg_ret": 0.1365,
      "samples": 6632,
      "ic": 0
    },
    "VOLR0.8-1.2": {
      "type": "VOLR",
      "condition": "VOLR0.8-1.2",
      "factor": "vol_ratio",
      "range": "0.8-1.2",
      "up_ratio": 50.68,
      "avg_ret": 0.1925,
      "samples": 25710,
      "ic": 0.004353
    },
    "VR120-150": {
      "type": "VR",
      "condition": "VR120-150",
      "factor": "vr_20",
      "range": "120-150",
      "up_ratio": 50.64,
      "avg_ret": 0.2332,
      "samples": 9716,
      "ic": -0.012286
    },
    "RSI55-65|VR150-200": {
      "type": "RSI+VR",
      "condition": "RSI55-65|VR150-200",
      "factor1": "rsi_14",
      "range1": "55-65",
      "factor2": "vr_20",
      "range2": "150-200",
      "up_ratio": 50.36,
      "avg_ret": 0.2529,
      "samples": 3227,
      "ic": 0
    },
    "Pct-2%~+2%|VR120-150": {
      "type": "Pct+VR",
      "condition": "Pct-2%~+2%|VR120-150",
      "factor1": "pct_1d",
      "range1": "-2%~+2%",
      "factor2": "vr_20",
      "range2": "120-150",
      "up_ratio": 50.29,
      "avg_ret": 0.1993,
      "samples": 6488,
      "ic": 0
    },
    "RSI35-45|VR80-120": {
      "type": "RSI+VR",
      "condition": "RSI35-45|VR80-120",
      "factor1": "rsi_14",
      "range1": "35-45",
      "factor2": "vr_20",
      "range2": "80-120",
      "up_ratio": 50.26,
      "avg_ret": 0.1187,
      "samples": 4111,
      "ic": 0
    },
    "VOLR0.5-0.8": {
      "type": "VOLR",
      "condition": "VOLR0.5-0.8",
      "factor": "vol_ratio",
      "range": "0.5-0.8",
      "up_ratio": 50.25,
      "avg_ret": 0.1511,
      "samples": 14134,
      "ic": 0.004353
    },
    "RSI55-65|KDJ50-80": {
      "type": "RSI+KDJ",
      "condition": "RSI55-65|KDJ50-80",
      "factor1": "rsi_14",
      "range1": "55-65",
      "factor2": "kdj_j",
      "range2": "50-80",
      "up_ratio": 50.15,
      "avg_ret": 0.2358,
      "samples": 3442,
      "ic": 0
    },
    "VR80-120": {
      "type": "VR",
      "condition": "VR80-120",
      "factor": "vr_20",
      "range": "80-120",
      "up_ratio": 50.14,
      "avg_ret": 0.139,
      "samples": 15410,
      "ic": -0.012286
    },
    "Pct-2%~+2%|VR80-120": {
      "type": "Pct+VR",
      "condition": "Pct-2%~+2%|VR80-120",
      "factor1": "pct_1d",
      "range1": "-2%~+2%",
      "factor2": "vr_20",
      "range2": "80-120",
      "up_ratio": 50.14,
      "avg_ret": 0.1243,
      "samples": 10716,
      "ic": 0
    },
    "PMA200.95-1.0": {
      "type": "PMA20",
      "condition": "PMA200.95-1.0",
      "factor": "price_ma20",
      "range": "0.95-1.0",
      "up_ratio": 50.04,
      "avg_ret": 0.1337,
      "samples": 17227,
      "ic": -0.039228
    },
    "CCI0~50": {
      "type": "CCI",
      "condition": "CCI0~50",
      "factor": "cci_14",
      "range": "0~50",
      "up_ratio": 49.95,
      "avg_ret": 0.1797,
      "samples": 7647,
      "ic": -0.020142
    },
    "Pct-2%~+2%|KDJ20-50": {
      "type": "Pct+KDJ",
      "condition": "Pct-2%~+2%|KDJ20-50",
      "factor1": "pct_1d",
      "range1": "-2%~+2%",
      "factor2": "kdj_j",
      "range2": "20-50",
      "up_ratio": 49.81,
      "avg_ret": 0.1465,
      "samples": 8228,
      "ic": 0
    },
    "CCI-50~0": {
      "type": "CCI",
      "condition": "CCI-50~0",
      "factor": "cci_14",
      "range": "-50~0",
      "up_ratio": 49.57,
      "avg_ret": 0.1516,
      "samples": 7379,
      "ic": -0.020142
    },
    "RSI45-55|VR80-120": {
      "type": "RSI+VR",
      "condition": "RSI45-55|VR80-120",
      "factor1": "rsi_14",
      "range1": "45-55",
      "factor2": "vr_20",
      "range2": "80-120",
      "up_ratio": 49.53,
      "avg_ret": 0.1599,
      "samples": 4276,
      "ic": 0
    },
    "VR150-200": {
      "type": "VR",
      "condition": "VR150-200",
      "factor": "vr_20",
      "range": "150-200",
      "up_ratio": 49.46,
      "avg_ret": 0.2319,
      "samples": 9517,
      "ic": -0.012286
    },
    "PMA201.0-1.05": {
      "type": "PMA20",
      "condition": "PMA201.0-1.05",
      "factor": "price_ma20",
      "range": "1.0-1.05",
      "up_ratio": 49.4,
      "avg_ret": 0.1696,
      "samples": 16881,
      "ic": -0.039228
    },
    "VOLR1.2-1.5": {
      "type": "VOLR",
      "condition": "VOLR1.2-1.5",
      "factor": "vol_ratio",
      "range": "1.2-1.5",
      "up_ratio": 49.11,
      "avg_ret": 0.2169,
      "samples": 6846,
      "ic": 0.004353
    },
    "PMA201.05-1.1": {
      "type": "PMA20",
      "condition": "PMA201.05-1.1",
      "factor": "price_ma20",
      "range": "1.05-1.1",
      "up_ratio": 48.98,
      "avg_ret": 0.3115,
      "samples": 6094,
      "ic": -0.039228
    },
    "Pct-2%~+2%|KDJ50-80": {
      "type": "Pct+KDJ",
      "condition": "Pct-2%~+2%|KDJ50-80",
      "factor1": "pct_1d",
      "range1": "-2%~+2%",
      "factor2": "kdj_j",
      "range2": "50-80",
      "up_ratio": 48.94,
      "avg_ret": 0.1651,
      "samples": 8505,
      "ic": 0
    },
    "Pct-2%~+2%|VR150-200": {
      "type": "Pct+VR",
      "condition": "Pct-2%~+2%|VR150-200",
      "factor1": "pct_1d",
      "range1": "-2%~+2%",
      "factor2": "vr_20",
      "range2": "150-200",
      "up_ratio": 48.87,
      "avg_ret": 0.1951,
      "samples": 5975,
      "ic": 0
    },
    "CCI50~100": {
      "type": "CCI",
      "condition": "CCI50~100",
      "factor": "cci_14",
      "range": "50~100",
      "up_ratio": 48.78,
      "avg_ret": 0.2036,
      "samples": 8449,
      "ic": -0.020142
    },
    "Pct-2%~+2%|KDJ>80": {
      "type": "Pct+KDJ",
      "condition": "Pct-2%~+2%|KDJ>80",
      "factor1": "pct_1d",
      "range1": "-2%~+2%",
      "factor2": "kdj_j",
      "range2": ">80",
      "up_ratio": 48.51,
      "avg_ret": 0.1334,
      "samples": 6036,
      "ic": 0
    },
    "VR>200": {
      "type": "VR",
      "condition": "VR>200",
      "factor": "vr_20",
      "range": ">200",
      "up_ratio": 48.35,
      "avg_ret": 0.1482,
      "samples": 5983,
      "ic": -0.012286
    },
    "PMA51.0-1.05": {
      "type": "PMA5",
      "condition": "PMA51.0-1.05",
      "factor": "price_ma5",
      "range": "1.0-1.05",
      "up_ratio": 48.34,
      "avg_ret": 0.174,
      "samples": 23361,
      "ic": -0.054113
    },
    "Pct-2%~+2%|VR>200": {
      "type": "Pct+VR",
      "condition": "Pct-2%~+2%|VR>200",
      "factor1": "pct_1d",
      "range1": "-2%~+2%",
      "factor2": "vr_20",
      "range2": ">200",
      "up_ratio": 48.23,
      "avg_ret": 0.1665,
      "samples": 3409,
      "ic": 0
    },
    "CCI>100": {
      "type": "CCI",
      "condition": "CCI>100",
      "factor": "cci_14",
      "range": ">100",
      "up_ratio": 46.35,
      "avg_ret": 0.1223,
      "samples": 9033,
      "ic": -0.020142
    },
    "VOLR1.5-2.0": {
      "type": "VOLR",
      "condition": "VOLR1.5-2.0",
      "factor": "vol_ratio",
      "range": "1.5-2.0",
      "up_ratio": 45.88,
      "avg_ret": -0.0339,
      "samples": 3230,
      "ic": 0.004353
    }
  },
  "metadata": {
    "version": "v4.7",
    "created": "2026-04-29",
    "total_samples": 0,
    "last_updated": "2026-04-30 09:31"
  }
}